varannote/__init__.py
varannote/__main__.py
varannote/cli.py
varannote/config.yaml
varannote/core/__init__.py
varannote/core/annotator.py
varannote/core/pathogenicity.py
varannote/databases/__init__.py
varannote/databases/clingen.py
varannote/databases/clinvar.py
varannote/databases/cosmic.py
varannote/databases/dbsnp.py
varannote/databases/ensembl.py
varannote/databases/gnomad.py
varannote/databases/hgmd.py
varannote/databases/omim.py
varannote/databases/pharmgkb.py
varannote/tools/__init__.py
varannote/tools/annotator.py
varannote/tools/compound_het.py
varannote/tools/pathogenicity.py
varannote/tools/pharmacogenomics.py
varannote/tools/population_freq.py
varannote/tools/segregation.py
varannote/utils/__init__.py
varannote/utils/annotation_db.py
varannote/utils/async_api.py
varannote/utils/config_manager.py
varannote/utils/filters.py
varannote/utils/logger.py
varannote/utils/real_annotation_db.py
varannote/utils/vcf_parser.py
varannote-1.0.8.dist-info/licenses/LICENSE
varannote-1.0.8.dist-info/METADATA
varannote-1.0.8.dist-info/WHEEL
varannote-1.0.8.dist-info/entry_points.txt
varannote-1.0.8.dist-info/top_level.txt
varannote-1.0.8.dist-info/RECORD
