Metadata-Version: 2.4
Name: varannote
Version: 1.0.8
Summary: Comprehensive Variant Analysis & Annotation Suite
Home-page: https://github.com/AtaUmutOZSOY/VarAnnote
Author: Ata Umut ÖZSOY
Author-email: Ata Umut ÖZSOY <ataumut7@gmail.com>
Maintainer-email: Ata Umut ÖZSOY <ataumut7@gmail.com>
License-Expression: MIT
Project-URL: Homepage, https://github.com/AtaUmutOZSOY/VarAnnote
Project-URL: Repository, https://github.com/AtaUmutOZSOY/VarAnnote
Project-URL: Documentation, https://varannote.readthedocs.io/
Project-URL: Bug Tracker, https://github.com/AtaUmutOZSOY/VarAnnote/issues
Keywords: bioinformatics,genomics,variant-annotation,clinical-genomics
Classifier: Development Status :: 5 - Production/Stable
Classifier: Intended Audience :: Science/Research
Classifier: Topic :: Scientific/Engineering :: Bio-Informatics
Classifier: Programming Language :: Python :: 3
Classifier: Programming Language :: Python :: 3.8
Classifier: Programming Language :: Python :: 3.9
Classifier: Programming Language :: Python :: 3.10
Classifier: Programming Language :: Python :: 3.11
Classifier: Programming Language :: Python :: 3.12
Requires-Python: >=3.8
License-File: LICENSE
Requires-Dist: click>=8.0.0
Requires-Dist: requests>=2.25.0
Requires-Dist: pandas>=1.3.0
Requires-Dist: numpy>=1.21.0
Requires-Dist: tqdm>=4.60.0
Requires-Dist: colorama>=0.4.4
Requires-Dist: tabulate>=0.8.9
Requires-Dist: pyyaml>=5.4.0
Requires-Dist: jsonschema>=3.2.0
Requires-Dist: urllib3>=1.26.0
Requires-Dist: certifi>=2021.5.30
Requires-Dist: charset-normalizer>=2.0.0
Requires-Dist: idna>=3.2
Requires-Dist: python-dateutil>=2.8.0
Requires-Dist: pytz>=2021.1
Requires-Dist: six>=1.16.0
Dynamic: author
Dynamic: home-page
Dynamic: license-file
Dynamic: requires-python
